nomad_camels_sandbox/CAMELS_sandbox.py
nomad_camels_sandbox/__init.py
nomad_camels_sandbox/server_signals.py
nomad_camels_sandbox/digitaltwins/__init__.py
nomad_camels_sandbox/digitaltwins/diode.py
nomad_camels_sandbox/digitaltwins/dmm.py
nomad_camels_sandbox/digitaltwins/experiment.py
nomad_camels_sandbox/digitaltwins/heater.py
nomad_camels_sandbox/digitaltwins/peltierelement.py
nomad_camels_sandbox/digitaltwins/ptxxxx.py
nomad_camels_sandbox/digitaltwins/semiconductor_resistor.py
nomad_camels_sandbox/digitaltwins/smu.py
nomad_camels_sandbox-0.1.6.dist-info/LICENSE
nomad_camels_sandbox-0.1.6.dist-info/METADATA
nomad_camels_sandbox-0.1.6.dist-info/WHEEL
nomad_camels_sandbox-0.1.6.dist-info/top_level.txt
nomad_camels_sandbox-0.1.6.dist-info/RECORD
