Metadata-Version: 2.1
Name: nomad_camels_sandbox
Version: 0.1.6
Summary: This package provides a sandbox for NOMAD CAMELS for demo purposes.
Author-email: FAIRmat <nomad-camels@fau.de>
Project-URL: GitHub Page, https://github.com/FAU-LAP/NOMAD-CAMELS
Project-URL: Documentation, https://fau-lap.github.io/NOMAD-CAMELS/doc/instruments/instruments.html
Classifier: Programming Language :: Python :: 3
Classifier: License :: OSI Approved :: GNU Lesser General Public License v2 (LGPLv2)
Requires-Python: >=3.9.6
License-File: LICENSE
Requires-Dist: nomad-camels >=1.0.5
